setup.py
ml_probability/Binomialdistribution.py
ml_probability/Gaussiandistribution.py
ml_probability/Generaldistribution.py
ml_probability/__init__.py
ml_probability.egg-info/PKG-INFO
ml_probability.egg-info/SOURCES.txt
ml_probability.egg-info/dependency_links.txt
ml_probability.egg-info/not-zip-safe
ml_probability.egg-info/top_level.txt