Metadata-Version: 1.0
Name: ml-probability
Version: 1.0
Summary: Gaussian and Binomial distributions
Home-page: UNKNOWN
Author: Ikechukwu Njoku
Author-email: njokuiyke01@yahoo.com
License: UNKNOWN
Platform: UNKNOWN
